{
	"elims":
	{
		"models" : {
			"document" : {
				"description" : "A document, usually the last step of an application.",
                "properties" : {
                    "_id" : {
                        "description" : "Unique ID.",
                        "type" : "number",
                        "unique" : true
                    },
                    "title" : {
                        "description" : "Descriptive title.",
                        "type" : "string"
                    }
                },
                "relationships" : {
                    "belongsto" : ["user", "document_type"],
                    "hasmany" : []
                }
			}
		}
	}
}
