{
	"iriki":
	{
		"routes" : {
            "default" : {
                "init" : ["model"],
                "add" : [],
                "read" : ["id"],
                "edit" : ["id", []],
                "delete" : ["id"]
            },
			"alias" : {
				"about" : {
					"route" : "page",
					"action" : "about"
				},
                "api" : {
					"route" : "",
					"action" : ""
				},
                "test" : {
					"route" : "",
					"action" : ""
				}
			},
            "routes" : [
                "user",
                "session",
                "merchant"
            ]
		}
	}
}
